{
  "episode": 118,
  "id": 118,
  "date": "2013-12-25",
  "duration": "00:38:27",
  "live": true,
  "people": [
    {
      "name": "Christian Schaefer",
      "team": [
        "2010-11-09"
      ],
      "twitter": "https://twitter.com/derSchepp"
    },
    {
      "name": "Hans Reinl",
      "team": [
        "2011-11-03"
      ],
      "twitter": "https://twitter.com/drublic"
    }
  ],
  "href": "http://workingdraft.de/118/",
  "audio": "http://workingdraft.de/podpress_trac/web/1920/0/wd-118.mp3",
  "topics": [
    {
      "name": "Coding, Fast and Slow: Developers and the Psychology of Overconfidence",
      "href": "http://blog.hut8labs.com/coding-fast-and-slow.html",
      "time": "00:00:33"
    }
  ],
  "news": [],
  "links": [
    {
      "name": "traceGL",
      "href": "https://trace.gl/",
      "time": "00:30:30"
    },
    {
      "name": "Listen, Watch And Share!",
      "href": "http://www.smashingmagazine.com/2013/04/19/podcasts-for-designers-developers/",
      "time": "00:30:30"
    },
    {
      "name": "PathFinding.js",
      "href": "https://github.com/qiao/PathFinding.js",
      "time": "00:30:30"
    },
    {
      "name": "PhantomCSS",
      "href": "http://tldr.huddle.com/blog/css-testing/",
      "time": "00:30:30"
    },
    {
      "name": "jQuery Annotated Source",
      "href": "http://robflaherty.github.io/jquery-annotated-source/",
      "time": "00:30:30"
    },
    {
      "name": "Snap.js",
      "href": "https://github.com/jakiestfu/Snap.js",
      "time": "00:30:30"
    },
    {
      "name": "Unheap",
      "href": "http://www.unheap.com/",
      "time": "00:30:30"
    }
  ],
  "randomSpec": [
    {
      "name": "<col> und <colgroup>",
      "href": "https://developer.mozilla.org/en-US/docs/HTML/Element/col",
      "time": "00:15:18"
    },
    {
      "name": "Erlaubte Zeichen in JavaScript Kommentaren",
      "href": "http://www.whatwg.org/specs/web-apps/current-work/#inline-documentation-for-external-scripts",
      "time": "00:15:18"
    }
  ]
}